{
  "project_info": {
    "project_number": "1014362208254",
    "project_id": "pizza-60b7a",
    "storage_bucket": "pizza-60b7a.appspot.com"
  },
  "client": [
    {
      "client_info": {
        "mobilesdk_app_id": "1:1014362208254:android:59a2f316dbd581f01232af",
        "android_client_info": {
          "package_name": "com.example.flutter_application_1"
        }
      },
      "oauth_client": [],
      "api_key": [
        {
          "current_key": "AIzaSyD39NPz0Ia72DRYEvYyesWrkiKNSOhe1Ew"
        }
      ],
      "services": {
        "appinvite_service": {
          "other_platform_oauth_client": []
        }
      }
    }
  ],
  "configuration_version": "1"
}